README.txt
bootstrap.py
buildout.cfg
setup.py
docs/HISTORY.txt
docs/TODO.txt
src/collective/__init__.py
src/collective.validationoverride.egg-info/PKG-INFO
src/collective.validationoverride.egg-info/SOURCES.txt
src/collective.validationoverride.egg-info/dependency_links.txt
src/collective.validationoverride.egg-info/entry_points.txt
src/collective.validationoverride.egg-info/namespace_packages.txt
src/collective.validationoverride.egg-info/not-zip-safe
src/collective.validationoverride.egg-info/requires.txt
src/collective.validationoverride.egg-info/top_level.txt
src/collective/validationoverride/README.txt
src/collective/validationoverride/__init__.py
src/collective/validationoverride/configure.zcml
src/collective/validationoverride/field.py
src/collective/validationoverride/tests.py