Metadata-Version: 1.0
Name: collective.validationoverride
Version: 0.1
Summary: Allow AT field validatiuon to fail for users who have an override permission
Home-page: http://pypi.python.org/pypi/collective.validationoverride
Author: Ross Patterson
Author-email: me@rpatterson.net
License: GPL
Platform: UNKNOWN
Classifier: Programming Language :: Python
Classifier: Topic :: Software Development :: Libraries :: Python Modules
